{"items":[{"title":"서울시 관악구 봉천동","header":false,"header_height":0,"item":{"id":343044,"images":[{"index":0,"count":1,"url":"http://i1.zigbang.com/items/343044/1.jpg"},{"index":1,"count":2,"url":"http://i1.zigbang.com/items/343044/2.jpg"},{"index":2,"count":3,"url":"http://i1.zigbang.com/items/343044/3.jpg"},{"index":3,"count":4,"url":"http://i1.zigbang.com/items/343044/4.jpg"},{"index":4,"count":5,"url":"http://i1.zigbang.com/items/343044/5.jpg"},{"index":5,"count":6,"url":"http://i1.zigbang.com/items/343044/6.jpg"},{"index":6,"count":7,"url":"http://i1.zigbang.com/items/343044/7.jpg"},{"index":7,"count":8,"url":"http://i1.zigbang.com/items/343044/8.jpg"},{"index":8,"count":9,"url":"http://i1.zigbang.com/items/343044/9.jpg"},{"index":9,"count":10,"url":"http://i1.zigbang.com/items/343044/10.jpg"},{"index":10,"count":11,"url":"http://i1.zigbang.com/items/343044/11.jpg"}],"is_realestate":true,"is_direct":false,"is_room":false,"is_type_room":false,"rent":50,"deposit":3000,"is_deposit_only":false,"floor":"1층","floor_all":"4층","local1":"서울시","local2":"관악구","local3":"봉천동","title":"초 역세권 남향 전용넓음","room_type":"쓰리룸+","building_type":"다세대건물","room_gubun_code":"01","status":"광고종료","is_status_open":false,"is_status_close":true,"view_count":367,"images_count":11,"updated_at":"1년 전","read_updated_at":"1/1/0001 12:00:00 AM","size_m2":"66.12","size":20.0,"size_m2_contract":"-","size_contract":0.0,"address1":"서울시 관악구 봉천동","near_subways":"봉천역(2호선), 서울대입구역(2호선), 신림역(2호선)","random_location":"37.4845154122946,126.94592091456","options":"싱크대, 신발장","manage_cost":"없음","manage_cost_inc":"-","parking":"가능","elevator":"없음","movein_date":"12월5일이후","description":"* 방3칸이 모두 큼 (침대 책상 모두 들어가도 공간좋음)<br />* 보증금 조정하여 월세가능함<br />* 12월5일 이후 공실로 올수리예정<br />* 발코니 있고 주방공간에 모두 들어가도 공간이 좋음<br />* 5식구 거주하여 살림이 많아 지저분해보이나 저렴한 가격에 넓은집 찜하세요 <br />* 부동산에서 보기엔 가격대비 공간이 좋아 수리 끝나면 주인이 맘이 틀려질까 걱정이네요 ","description_og":"* 방3칸이 모두 큼 (침대 책상 모두 들어가도 공간좋음)\n* 보증금 조정하여 월세가능함\n* 12월5일 이후 공실로 올수리예정\n* 발코니 있고 주방공간에 모두 들어가도 공간이 좋음\n* 5식구 거주하여 살림이 많아 지저분해보이나 저렴한 가격에 넓은집 찜하세요 \n* 부동산에서 보기엔 가격대비 공간이 좋아 수리 끝나면 주인이 맘이 틀려질까 걱정이네요 ","pets_text":"확인필요","loan_text":"확인필요","room_direction_text":"확인필요","is_owner":null,"images_thumbnail":"","is_zzim":false,"secret_memo":null,"user_no":58596,"user_has_penalty":false,"user_has_no_penalty":true,"user_name":"대표공인중개사(박정남)","user_phone":"010-8514-2179","original_user_phone":"010-8514-2179","user_mobile":"010-8514-2179","user_email":"pjn0527@naver.com","agent_name":"스마트공인중개사(박정남)","agent_phone":"010-8514-2179","agent_mobile":"010-8514-2179","agent_email":"pjn0527@naver.com","agent_local1":"서울시","agent_local2":"관악구","agent_address1":"서울특별시 관악구 봉천동 932-7번지","building":null,"contract":"서울특별시","bjd_code":"1162010100","bonbun_code":"909","bubun_code":"36","address2":"909-36","address3":null,"is_premium":false,"is_premium2":false,"profile_url":"http://api.zigbang.com/ic/profile/608478/21957e47747dc8ab11965f85fa24bcb710f8f2ce.jpg"}}],"count_agent":1,"count_direct":0}